{"http://rdfs.org/ns/void#inDataset": ["http://www.opengis.net/geoepsg_dataset"], "http://www.opengis.net/ont/crs/area_of_use": ["http://www.opengis.net/def/crs/EPSG/0/6182_area_of_use"], "http://www.opengis.net/ont/crs/asProj4": ["+vunits=m +no_defs +type=crs"], "http://www.opengis.net/ont/crs/asProjJSON": ["{'$schema':'https://proj.org/schemas/v0.7/projjson.schema.json','type':'VerticalCRS','name':'Cais da Madalena height','datum':{'type':'VerticalReferenceFrame','name':'Cais da Madalena'},'coordinate_system':{'subtype':'vertical','axis':[{'name':'Gravity-related height','abbreviation':'H','direction':'up','unit':'metre'}]},'scope':'Geodesy, engineering survey, topographic mapping.','area':'Portugal - central Azores - Pico island onshore.','bbox':{'south_latitude':38.32,'west_longitude':-28.61,'north_latitude':38.61,'east_longitude':-27.98},'id':{'authority':'EPSG','code':6182}}"], "http://www.opengis.net/ont/crs/asWKT": ["VERTCRS['Cais da Madalena height',VDATUM['Cais da Madalena'],CS[vertical,1],AXIS['gravity-related height (H)',up,LENGTHUNIT['metre',1]],USAGE[SCOPE['Geodesy, engineering survey, topographic mapping.'],AREA['Portugal - central Azores - Pico island onshore.'],BBOX[38.32,-28.61,38.61,-27.98]],ID['EPSG',6182]]"], "http://www.opengis.net/ont/crs/coordinateSystem": ["http://www.opengis.net/def/crs/EPSG/0/6182_cs"], "http://www.opengis.net/ont/crs/datum": ["http://www.opengis.net/ont/crs/datum/Cais_da_Madalena"], "http://www.opengis.net/ont/crs/epsgCode": ["EPSG:6182"], "http://www.opengis.net/ont/crs/isApplicableTo": ["http://www.opengis.net/ont/crs/isbody/Earth"], "http://www.opengis.net/ont/crs/isBound": ["false"], "http://www.opengis.net/ont/crs/isGeocentric": ["false"], "http://www.opengis.net/ont/crs/isGeographic": ["false"], "http://www.opengis.net/ont/crs/isProjected": ["false"], "http://www.opengis.net/ont/crs/isVertical": ["true"], "http://www.w3.org/1999/02/22-rdf-syntax-ns#type": ["http://www.opengis.net/ont/crs/VerticalCRS", "http://www.w3.org/2002/07/owl#NamedIndividual", "http://www.w3.org/ns/prov-o/Entity"], "http://www.w3.org/2000/01/rdf-schema#label": ["Cais da Madalena height"]}