{"http://rdfs.org/ns/void#inDataset": ["http://www.opengis.net/geoepsg_dataset"], "http://www.w3.org/1999/02/22-rdf-syntax-ns#type": ["http://www.w3.org/2002/07/owl#NamedIndividual", "http://www.w3.org/ns/prov-o/Entity", "https://w3id.org/geosrs/CompoundCRS"], "http://www.w3.org/2000/01/rdf-schema#label": ["Tokyo + JSLD72 height"], "https://w3id.org/geosrs/area_of_use": ["http://www.opengis.net/def/crs/EPSG/0/6700_area_of_use"], "https://w3id.org/geosrs/asProj4": ["+proj=longlat +ellps=bessel +vunits=m +no_defs +type=crs"], "https://w3id.org/geosrs/asProjJSON": ["{'$schema':'https://proj.org/schemas/v0.7/projjson.schema.json','type':'CompoundCRS','name':'Tokyo + JSLD72 height','components':[{'type':'GeographicCRS','name':'Tokyo','datum':{'type':'GeodeticReferenceFrame','name':'Tokyo','ellipsoid':{'name':'Bessel 1841','semi_major_axis':6377397.155,'inverse_flattening':299.1528128}},'coordinate_system':{'subtype':'ellipsoidal','axis':[{'name':'Geodetic latitude','abbreviation':'Lat','direction':'north','unit':'degree'},{'name':'Geodetic longitude','abbreviation':'Lon','direction':'east','unit':'degree'}]}},{'type':'VerticalCRS','name':'JSLD72 height','datum':{'type':'VerticalReferenceFrame','name':'Japanese Standard Levelling Datum 1972'},'coordinate_system':{'subtype':'vertical','axis':[{'name':'Gravity-related height','abbreviation':'H','direction':'up','unit':'metre'}]}}],'scope':'Engineering survey, topographic mapping.','area':'Japan - onshore mainland - Hokkaido.','bbox':{'south_latitude':41.34,'west_longitude':139.7,'north_latitude':45.54,'east_longitude':145.87},'id':{'authority':'EPSG','code':6700}}"], "https://w3id.org/geosrs/asWKT": ["COMPOUNDCRS['Tokyo + JSLD72 height',GEOGCRS['Tokyo',DATUM['Tokyo',ELLIPSOID['Bessel 1841',6377397.155,299.1528128,LENGTHUNIT['metre',1]]],PRIMEM['Greenwich',0,ANGLEUNIT['degree',0.0174532925199433]],CS[ellipsoidal,2],AXIS['geodetic latitude (Lat)',north,ORDER[1],ANGLEUNIT['degree',0.0174532925199433]],AXIS['geodetic longitude (Lon)',east,ORDER[2],ANGLEUNIT['degree',0.0174532925199433]]],VERTCRS['JSLD72 height',VDATUM['Japanese Standard Levelling Datum 1972'],CS[vertical,1],AXIS['gravity-related height (H)',up,LENGTHUNIT['metre',1]]],USAGE[SCOPE['Engineering survey, topographic mapping.'],AREA['Japan - onshore mainland - Hokkaido.'],BBOX[41.34,139.7,45.54,145.87]],ID['EPSG',6700]]"], "https://w3id.org/geosrs/datum": ["https://w3id.org/geosrs/datum/Tokyo"], "https://w3id.org/geosrs/epsgCode": ["EPSG:6700"], "https://w3id.org/geosrs/includesSRS": ["http://www.opengis.net/def/crs/EPSG/0/4301", "http://www.opengis.net/def/crs/EPSG/0/6693"], "https://w3id.org/geosrs/isApplicableTo": ["http://www.opengis.net/ont/crs/isbody/Earth"], "https://w3id.org/geosrs/isBound": ["false"], "https://w3id.org/geosrs/isGeocentric": ["false"], "https://w3id.org/geosrs/isGeographic": ["true"], "https://w3id.org/geosrs/isProjected": ["false"], "https://w3id.org/geosrs/isVertical": ["true"]}