{"http://rdfs.org/ns/void#inDataset": ["http://www.opengis.net/geoepsg_dataset"], "http://www.w3.org/1999/02/22-rdf-syntax-ns#type": ["https://w3id.org/geosrs/CentralCylindricalProjection"], "http://www.w3.org/2000/01/rdf-schema#comment": ["May be defined using LCC (1SP) method (EPSG method code 9801) with value of latitude for natural origin as latitude at false origin here and scale factor = 0.9995770671."], "http://www.w3.org/2000/01/rdf-schema#label": ["EPSG Arctic LCC zone 6-22: Lambert Conic Conformal (2SP)"], "http://xmlns.com/foaf/0.1/image": ["https://situx.github.io/proj4rdf/projections/CentralCylindricalProjection.svg"], "https://w3id.org/geosrs/accuracy": ["-1.0"], "https://w3id.org/geosrs/area_of_use": ["http://www.opengis.net/ont/crs/areaofuse/EPSG_Arctic_LCC_zone_6-22_area_of_use"], "https://w3id.org/geosrs/asProj4": ["+proj=pipeline +step +proj=axisswap +order=2,1 +step +proj=unitconvert +xy_in=deg +xy_out=rad +step +proj=lcc +lat_0=68.6874755555556 +lon_0=-94 +lat_1=70.3333333333333 +lat_2=67 +x_0=22500000 +y_0=6500000 +ellps=GRS80"], "https://w3id.org/geosrs/asProjJSON": ["{'$schema':'https://proj.org/schemas/v0.7/projjson.schema.json','type':'Conversion','name':'EPSG Arctic LCC zone 6-22','method':{'name':'Lambert Conic Conformal (2SP)','id':{'authority':'EPSG','code':9802}},'parameters':[{'name':'Latitude of false origin','value':68.6874755555556,'unit':'degree','id':{'authority':'EPSG','code':8821}},{'name':'Longitude of false origin','value':-94,'unit':'degree','id':{'authority':'EPSG','code':8822}},{'name':'Latitude of 1st standard parallel','value':70.3333333333333,'unit':'degree','id':{'authority':'EPSG','code':8823}},{'name':'Latitude of 2nd standard parallel','value':67,'unit':'degree','id':{'authority':'EPSG','code':8824}},{'name':'Easting at false origin','value':22500000,'unit':'metre','id':{'authority':'EPSG','code':8826}},{'name':'Northing at false origin','value':6500000,'unit':'metre','id':{'authority':'EPSG','code':8827}}],'id':{'authority':'EPSG','code':6043}}"], "https://w3id.org/geosrs/asWKT": ["CONVERSION['EPSG Arctic LCC zone 6-22',METHOD['Lambert Conic Conformal (2SP)',ID['EPSG',9802]],PARAMETER['Latitude of false origin',68.6874755555556,ANGLEUNIT['degree',0.0174532925199433],ID['EPSG',8821]],PARAMETER['Longitude of false origin',-94,ANGLEUNIT['degree',0.0174532925199433],ID['EPSG',8822]],PARAMETER['Latitude of 1st standard parallel',70.3333333333333,ANGLEUNIT['degree',0.0174532925199433],ID['EPSG',8823]],PARAMETER['Latitude of 2nd standard parallel',67,ANGLEUNIT['degree',0.0174532925199433],ID['EPSG',8824]],PARAMETER['Easting at false origin',22500000,LENGTHUNIT['metre',1],ID['EPSG',8826]],PARAMETER['Northing at false origin',6500000,LENGTHUNIT['metre',1],ID['EPSG',8827]],ID['EPSG',6043]]"], "https://w3id.org/geosrs/eastingAtFalseOrigin": ["22500000.0"], "https://w3id.org/geosrs/has_ballpark_transformation": ["false"], "https://w3id.org/geosrs/latitudeOf1StStandardParallel": ["70.33333"], "https://w3id.org/geosrs/latitudeOf2NdStandardParallel": ["67.0"], "https://w3id.org/geosrs/latitudeOfFalseOrigin": ["68.68748"], "https://w3id.org/geosrs/longitudeOfFalseOrigin": ["-94.0"], "https://w3id.org/geosrs/method_name": ["Lambert Conic Conformal (2SP)"], "https://w3id.org/geosrs/northingAtFalseOrigin": ["6500000.0"], "https://w3id.org/geosrs/scope": ["Exploration and development, mapping."]}