{"http://rdfs.org/ns/void#inDataset": ["http://www.opengis.net/geoepsg_dataset"], "http://www.w3.org/1999/02/22-rdf-syntax-ns#type": ["http://www.w3.org/2002/07/owl#NamedIndividual", "http://www.w3.org/ns/prov-o/Entity", "https://w3id.org/geosrs/VerticalCRS"], "http://www.w3.org/2000/01/rdf-schema#label": ["Genoa 1942 height"], "https://w3id.org/geosrs/area_of_use": ["http://www.opengis.net/def/crs/EPSG/0/5214_area_of_use"], "https://w3id.org/geosrs/asProj4": ["+vunits=m +no_defs +type=crs"], "https://w3id.org/geosrs/asProjJSON": ["{'$schema':'https://proj.org/schemas/v0.7/projjson.schema.json','type':'VerticalCRS','name':'Genoa 1942 height','datum':{'type':'VerticalReferenceFrame','name':'Genoa 1942'},'coordinate_system':{'subtype':'vertical','axis':[{'name':'Gravity-related height','abbreviation':'H','direction':'up','unit':'metre'}]},'scope':'Geodesy, engineering survey, topographic mapping.','area':'Italy - mainland (including San Marino and Vatican City State) and Sicily.','bbox':{'south_latitude':36.59,'west_longitude':6.62,'north_latitude':47.1,'east_longitude':18.58},'id':{'authority':'EPSG','code':5214}}"], "https://w3id.org/geosrs/asWKT": ["VERTCRS['Genoa 1942 height',VDATUM['Genoa 1942'],CS[vertical,1],AXIS['gravity-related height (H)',up,LENGTHUNIT['metre',1]],USAGE[SCOPE['Geodesy, engineering survey, topographic mapping.'],AREA['Italy - mainland (including San Marino and Vatican City State) and Sicily.'],BBOX[36.59,6.62,47.1,18.58]],ID['EPSG',5214]]"], "https://w3id.org/geosrs/coordinateSystem": ["http://www.opengis.net/def/crs/EPSG/0/5214_cs"], "https://w3id.org/geosrs/datum": ["https://w3id.org/geosrs/datum/Genoa_1942"], "https://w3id.org/geosrs/epsgCode": ["EPSG:5214"], "https://w3id.org/geosrs/isApplicableTo": ["http://www.opengis.net/ont/crs/isbody/Earth"], "https://w3id.org/geosrs/isBound": ["false"], "https://w3id.org/geosrs/isGeocentric": ["false"], "https://w3id.org/geosrs/isGeographic": ["false"], "https://w3id.org/geosrs/isProjected": ["false"], "https://w3id.org/geosrs/isVertical": ["true"]}