{"http://rdfs.org/ns/void#inDataset": ["http://www.opengis.net/geoepsg_dataset"], "http://www.opengis.net/ont/crs/area_of_use": ["http://www.opengis.net/def/crs/EPSG/0/6641_area_of_use"], "http://www.opengis.net/ont/crs/asProj4": ["+vunits=m +no_defs +type=crs"], "http://www.opengis.net/ont/crs/asProjJSON": ["{'$schema':'https://proj.org/schemas/v0.7/projjson.schema.json','type':'VerticalCRS','name':'PRVD02 height','datum':{'type':'VerticalReferenceFrame','name':'Puerto Rico Vertical Datum of 2002'},'coordinate_system':{'subtype':'vertical','axis':[{'name':'Gravity-related height','abbreviation':'H','direction':'up','unit':'metre'}]},'scope':'Geodesy, engineering survey, topographic mapping.','area':'Puerto Rico - onshore.','bbox':{'south_latitude':17.87,'west_longitude':-67.97,'north_latitude':18.57,'east_longitude':-65.19},'id':{'authority':'EPSG','code':6641}}"], "http://www.opengis.net/ont/crs/asWKT": ["VERTCRS['PRVD02 height',VDATUM['Puerto Rico Vertical Datum of 2002'],CS[vertical,1],AXIS['gravity-related height (H)',up,LENGTHUNIT['metre',1]],USAGE[SCOPE['Geodesy, engineering survey, topographic mapping.'],AREA['Puerto Rico - onshore.'],BBOX[17.87,-67.97,18.57,-65.19]],ID['EPSG',6641]]"], "http://www.opengis.net/ont/crs/coordinateSystem": ["http://www.opengis.net/def/crs/EPSG/0/6641_cs"], "http://www.opengis.net/ont/crs/datum": ["http://www.opengis.net/ont/crs/datum/Puerto_Rico_Vertical_Datum_of_2002"], "http://www.opengis.net/ont/crs/epsgCode": ["EPSG:6641"], "http://www.opengis.net/ont/crs/isApplicableTo": ["http://www.opengis.net/ont/crs/isbody/Earth"], "http://www.opengis.net/ont/crs/isBound": ["false"], "http://www.opengis.net/ont/crs/isGeocentric": ["false"], "http://www.opengis.net/ont/crs/isGeographic": ["false"], "http://www.opengis.net/ont/crs/isProjected": ["false"], "http://www.opengis.net/ont/crs/isVertical": ["true"], "http://www.w3.org/1999/02/22-rdf-syntax-ns#type": ["http://www.opengis.net/ont/crs/VerticalCRS", "http://www.w3.org/2002/07/owl#NamedIndividual", "http://www.w3.org/ns/prov-o/Entity"], "http://www.w3.org/2000/01/rdf-schema#label": ["PRVD02 height"]}