{"http://rdfs.org/ns/void#inDataset": ["http://www.opengis.net/geoepsg_dataset"], "http://www.w3.org/1999/02/22-rdf-syntax-ns#type": ["https://w3id.org/geosrs/MercatorProjection"], "http://www.w3.org/2000/01/rdf-schema#comment": ["See proj code 7462 for authoritative metric definition. Replaces and emulates WCCS zone."], "http://www.w3.org/2000/01/rdf-schema#label": ["WISCRS Oconto County (ftUS): Transverse Mercator"], "http://xmlns.com/foaf/0.1/image": ["https://situx.github.io/proj4rdf/projections/MercatorProjection.svg"], "https://w3id.org/geosrs/accuracy": ["-1.0"], "https://w3id.org/geosrs/area_of_use": ["http://www.opengis.net/ont/crs/areaofuse/WISCRS_Oconto_County__ftUS__area_of_use"], "https://w3id.org/geosrs/asProj4": ["+proj=pipeline +step +proj=axisswap +order=2,1 +step +proj=unitconvert +xy_in=deg +xy_out=rad +step +proj=tmerc +lat_0=44.3972222222222 +lon_0=-87.9083333333333 +k=1.0000236869 +x_0=182880.367589535 +y_0=0.00335280670561341 +ellps=GRS80 +step +proj=unitconvert +xy_in=m +xy_out=us-ft"], "https://w3id.org/geosrs/asProjJSON": ["{'$schema':'https://proj.org/schemas/v0.7/projjson.schema.json','type':'Conversion','name':'WISCRS Oconto County (ftUS)','method':{'name':'Transverse Mercator','id':{'authority':'EPSG','code':9807}},'parameters':[{'name':'Latitude of natural origin','value':44.3972222222222,'unit':'degree','id':{'authority':'EPSG','code':8801}},{'name':'Longitude of natural origin','value':-87.9083333333333,'unit':'degree','id':{'authority':'EPSG','code':8802}},{'name':'Scale factor at natural origin','value':1.0000236869,'unit':'unity','id':{'authority':'EPSG','code':8805}},{'name':'False easting','value':600000.006,'unit':{'type':'LinearUnit','name':'US survey foot','conversion_factor':0.304800609601219},'id':{'authority':'EPSG','code':8806}},{'name':'False northing','value':0.011,'unit':{'type':'LinearUnit','name':'US survey foot','conversion_factor':0.304800609601219},'id':{'authority':'EPSG','code':8807}}],'id':{'authority':'EPSG','code':7463}}"], "https://w3id.org/geosrs/asWKT": ["CONVERSION['WISCRS Oconto County (ftUS)',METHOD['Transverse Mercator',ID['EPSG',9807]],PARAMETER['Latitude of natural origin',44.3972222222222,ANGLEUNIT['degree',0.0174532925199433],ID['EPSG',8801]],PARAMETER['Longitude of natural origin',-87.9083333333333,ANGLEUNIT['degree',0.0174532925199433],ID['EPSG',8802]],PARAMETER['Scale factor at natural origin',1.0000236869,SCALEUNIT['unity',1],ID['EPSG',8805]],PARAMETER['False easting',600000.006,LENGTHUNIT['US survey foot',0.304800609601219],ID['EPSG',8806]],PARAMETER['False northing',0.011,LENGTHUNIT['US survey foot',0.304800609601219],ID['EPSG',8807]],ID['EPSG',7463]]"], "https://w3id.org/geosrs/falseEasting": ["600000.0"], "https://w3id.org/geosrs/falseNorthing": ["0.011"], "https://w3id.org/geosrs/has_ballpark_transformation": ["false"], "https://w3id.org/geosrs/latitudeOfNaturalOrigin": ["44.39722"], "https://w3id.org/geosrs/longitudeOfNaturalOrigin": ["-87.90833"], "https://w3id.org/geosrs/method_name": ["Transverse Mercator"], "https://w3id.org/geosrs/scaleFactorAtNaturalOrigin": ["1.000024"], "https://w3id.org/geosrs/scope": ["Engineering survey."]}