{"title": "Datum: Kuwait Oil Company", "id": "nonns_Kuwait_Oil_Company", "links": [{"href": "https:/opengeospatial.github.io/ontology-crs/data/collections/nonns_Kuwait_Oil_Company/items/index.json", "rel": "items", "type": "application/json", "title": "Collection as JSON"}, {"href": "https:/opengeospatial.github.io/ontology-crs/data/collections/nonns_Kuwait_Oil_Company/items/indexc.html", "rel": "items", "type": "text/html", "title": "Collection as HTML"}, {"href": "https:/opengeospatial.github.io/ontology-crs/data/collections/nonns_Kuwait_Oil_Company/items/index.ttl", "rel": "collection", "type": "text/ttl", "title": "Collection as TTL"}], "itemType": "feature", "extent": {"spatial": {"bbox": [46.54, 28.53, 48.48, 30.09], "crs": "http://www.opengis.net/def/crs/EPSG/0/EPSG:CRS84"}}, "crs": "http://www.opengis.net/def/crs/EPSG/0/EPSG:CRS84"}